bosh_inventory/__init__.py
bosh_inventory/bosh_inventory.py
bosh_inventory-0.4.4.dist-info/LICENSE.txt
bosh_inventory-0.4.4.dist-info/METADATA
bosh_inventory-0.4.4.dist-info/WHEEL
bosh_inventory-0.4.4.dist-info/entry_points.txt
bosh_inventory-0.4.4.dist-info/top_level.txt
bosh_inventory-0.4.4.dist-info/RECORD
