Metadata-Version: 2.1
Name: bosh-inventory
Version: 0.4.4
Summary: Ansible dynamic inventory for bosh deployments
Home-page: https://github.com/SpringerPE/bosh-ansible-inventory
Author: Jose Riguera Lopez
Author-email: jose.riguera@springer.com
License: MIT
Download-URL: https://github.com/SpringerPE/bosh-ansible-inventory/releases/tag/v0.4.4
Keywords: bosh ansible inventory
Platform: UNKNOWN
Classifier: Development Status :: 5 - Production/Stable
Classifier: Intended Audience :: System Administrators
Classifier: Topic :: System :: Systems Administration
Classifier: License :: OSI Approved :: MIT License
Classifier: Programming Language :: Python :: 2.7
Classifier: Programming Language :: Python :: 3
Requires-Dist: requests (>=2.20.0)
Requires-Dist: PyYAML (>=3.11)
